README.rst
setup.py
src/stackfull.py
src/stackfull.egg-info/PKG-INFO
src/stackfull.egg-info/SOURCES.txt
src/stackfull.egg-info/dependency_links.txt
src/stackfull.egg-info/not-zip-safe
src/stackfull.egg-info/top_level.txt