Metadata-Version: 1.1
Name: stackfull
Version: 1.0.0
Summary: Tools for stack-usage in Python expressions
Home-page: https://github.com/jsbueno/stackfull
Author: João S. O. Bueno
Author-email: gwidion@gmail.com
License: License :: OSI Approved :: Python Software Foundation License
Keywords: python expressions stack acelerator utils push pop
Platform: UNKNOWN
Classifier: Development Status :: 5 - Production/Stable
Classifier: Intended Audience :: End Users/Desktop
Classifier: Intended Audience :: Developers
Classifier: License :: OSI Approved :: GNU General Public License v3 or later (GPLv3+)
Classifier: License :: OSI Approved :: GNU Lesser General Public License v3 or later (LGPLv3+)
Classifier: License :: OSI Approved :: Python Software Foundation License
Classifier: Operating System :: OS Independent
Classifier: Programming Language :: Python
Classifier: Programming Language :: Python :: 3
Classifier: Programming Language :: Python :: Implementation :: PyPy
Classifier: Topic :: Software Development :: Libraries :: Python Modules
